tests/__init__.py
tests/test_schedule.py
uscschedule/__init__.py
uscschedule/exceptions.py
uscschedule/models.py
uscschedule/schedule.py
uscschedule/util.py
usc_schedule-1.0.1.dist-info/LICENSE
usc_schedule-1.0.1.dist-info/METADATA
usc_schedule-1.0.1.dist-info/WHEEL
usc_schedule-1.0.1.dist-info/top_level.txt
usc_schedule-1.0.1.dist-info/RECORD
