Metadata-Version: 2.1
Name: usc-schedule
Version: 1.0.1
Summary: A USC Class Schedule API wrapper
Home-page: https://github.com/switchswap/USC-schedule
Author: Swapnil Patel
Author-email: swapnil@usc.edu
License: UNKNOWN
Platform: UNKNOWN
Classifier: Programming Language :: Python
Classifier: Programming Language :: Python :: 3
Classifier: Programming Language :: Python :: 3.6
Classifier: License :: OSI Approved :: Apache Software License
Classifier: Operating System :: OS Independent
Classifier: Topic :: Education
Classifier: Topic :: Internet
Classifier: Topic :: Utilities
Classifier: Topic :: Software Development :: Libraries :: Python Modules
Requires-Python: >=3.6
Requires-Dist: requests
